{"name": "Po2_flat > 0.242236256599", "children": [{"name": "Po2_flat > 0.258756875992", "children": [{"name": "Po2_flat > 0.31766474247", "children": [{"name": "Ph2_flat > 78.0542755127", "children": [{"name": "0 of p"}, {"name": "0 of p"}]}, {"name": "Po2_flat > 0.317307114601", "children": [{"name": "1 of p"}, {"name": "0 of p"}]}]}, {"name": "Po2_flat > 0.25070130825", "children": [{"name": "Ph2_flat > 74.4371261597", "children": [{"name": "0 of p"}, {"name": "0 of p"}]}, {"name": "Ph2_flat > 94.9454193115", "children": [{"name": "0 of p"}, {"name": "0 of p"}]}]}]}, {"name": "Po2_flat > 0.204280614853", "children": [{"name": "Ph2_flat > 89.4960327148", "children": [{"name": "Ph2_flat > 106.202201843", "children": [{"name": "0 of p"}, {"name": "0 of p"}]}, {"name": "Po2_flat > 0.226972699165", "children": [{"name": "0 of p"}, {"name": "0 of p"}]}]}, {"name": "Po2_flat > 0.124890208244", "children": [{"name": "Ph2_flat > 65.0992584229", "children": [{"name": "0 of p"}, {"name": "1 of p"}]}, {"name": "Ph2_flat > 37.1872177124", "children": [{"name": "0 of p"}, {"name": "0 of p"}]}]}]}]}