{"name": "Po2_flat > 0.241693258286", "children": [{"name": "Po2_flat > 0.258756875992", "children": [{"name": "Po2_flat > 0.318546295166", "children": [{"name": "Ph2_flat > 70.5498962402", "children": [{"name": "Ph2_flat > 78.0542755127", "children": [{"name": "0 of p"}, {"name": "0 of p"}]}, {"name": "Ph2_flat > 69.3232116699", "children": [{"name": "1 of p"}, {"name": "0 of p"}]}]}, {"name": "Po2_flat > 0.285499095917", "children": [{"name": "Ph2_flat > 84.7650299072", "children": [{"name": "0 of p"}, {"name": "0 of p"}]}, {"name": "Po2_flat > 0.265557169914", "children": [{"name": "0 of p"}, {"name": "0 of p"}]}]}]}, {"name": "Ph2_flat > 86.8595504761", "children": [{"name": "Po2_flat > 0.24828851223", "children": [{"name": "Po2_flat > 0.257884860039", "children": [{"name": "0 of p"}, {"name": "0 of p"}]}, {"name": "Po2_flat > 0.247610807419", "children": [{"name": "0 of p"}, {"name": "0 of p"}]}]}, {"name": "Ph2_flat > 74.4253540039", "children": [{"name": "Po2_flat > 0.248528122902", "children": [{"name": "0 of p"}, {"name": "0 of p"}]}, {"name": "Ph2_flat > 73.3086776733", "children": [{"name": "0 of p"}, {"name": "0 of p"}]}]}]}]}, {"name": "Po2_flat > 0.124890208244", "children": [{"name": "Po2_flat > 0.199707150459", "children": [{"name": "Ph2_flat > 89.3681869507", "children": [{"name": "Ph2_flat > 106.748733521", "children": [{"name": "0 of p"}, {"name": "0 of p"}]}, {"name": "Po2_flat > 0.226988196373", "children": [{"name": "0 of p"}, {"name": "0 of p"}]}]}, {"name": "Ph2_flat > 61.3197174072", "children": [{"name": "Po2_flat > 0.138119459152", "children": [{"name": "0 of p"}, {"name": "0 of p"}]}, {"name": "Ph2_flat > 57.8691864014", "children": [{"name": "1 of p"}, {"name": "0 of p"}]}]}]}, {"name": "Po2_flat > 0.0472378730774", "children": [{"name": "Ph2_flat > 96.295211792", "children": [{"name": "Po2_flat > 0.120875835419", "children": [{"name": "0 of p"}, {"name": "0 of p"}]}, {"name": "Po2_flat > 0.112341046333", "children": [{"name": "0 of p"}, {"name": "1 of p"}]}]}, {"name": "0 of p"}]}]}]}