{"name": "Po2_flat > 0.241305232048", "children": [{"name": "Po2_flat > 0.260077118874", "children": [{"name": "Ph2_flat > 78.826675415", "children": [{"name": "Ph2_flat > 81.9385375977", "children": [{"name": "0 of p"}, {"name": "0 of p"}]}, {"name": "Ph2_flat > 78.7581176758", "children": [{"name": "1 of p"}, {"name": "0 of p"}]}]}, {"name": "Ph2_flat > 88.5658035278", "children": [{"name": "Po2_flat > 0.245193839073", "children": [{"name": "0 of p"}, {"name": "0 of p"}]}, {"name": "Po2_flat > 0.249908566475", "children": [{"name": "0 of p"}, {"name": "0 of p"}]}]}]}, {"name": "Po2_flat > 0.125267505646", "children": [{"name": "Po2_flat > 0.199707150459", "children": [{"name": "Ph2_flat > 89.8414077759", "children": [{"name": "0 of p"}, {"name": "0 of p"}]}, {"name": "Ph2_flat > 63.6501922607", "children": [{"name": "0 of p"}, {"name": "1 of p"}]}]}, {"name": "Ph2_flat > 37.1872177124", "children": [{"name": "Ph2_flat > 96.5519561768", "children": [{"name": "0 of p"}, {"name": "0 of p"}]}, {"name": "0 of p"}]}]}]}